aioworker/__init__.py
aioworker/worker.py
aioworker-0.2.0.dist-info/LICENSE
aioworker-0.2.0.dist-info/WHEEL
aioworker-0.2.0.dist-info/METADATA
aioworker-0.2.0.dist-info/RECORD
