Metadata-Version: 2.1
Name: aioworker
Version: 0.2.0
Summary: Python async worker
License: MIT
Keywords: aioworker,kafka,streaming,async
Author: Marcos Schroh
Author-email: schrohm@gmail.com
Requires-Python: >=3.8,<4.0
Classifier: License :: OSI Approved :: MIT License
Classifier: Programming Language :: Python :: 3
Classifier: Programming Language :: Python :: 3.8
Requires-Dist: aiotools (>=0.8.5,<0.9.0)
